<?xml version="1.0" encoding="UTF-8" standalone="yes"?>
<imgdir name="QuestCategory.img">
    <imgdir name="0">
        <int name="category" value="6"/>
        <string name="title" value="Hero From the Past, Aran"/>
    </imgdir>
    <imgdir name="1">
        <int name="category" value="7"/>
        <string name="title" value="Dragon Master, Evan"/>
    </imgdir>
    <imgdir name="2">
        <int name="category" value="8"/>
        <string name="title" value="Ruler of the Elves, Mercedes"/>
    </imgdir>
    <imgdir name="3">
        <string name="title" value="Job"/>
        <int name="category" value="10"/>
    </imgdir>
    <imgdir name="4">
        <string name="title" value="Cygnus Knights"/>
        <int name="category" value="15"/>
    </imgdir>
    <imgdir name="5">
        <string name="title" value="Resistance"/>
        <int name="category" value="16"/>
    </imgdir>
    <imgdir name="6">
        <string name="title" value="Beginner&apos;s Basics"/>
        <int name="category" value="2"/>
    </imgdir>
    <imgdir name="7">
        <string name="title" value="Maple Island"/>
        <int name="category" value="20"/>
    </imgdir>
    <imgdir name="8">
        <string name="title" value="Edelstein"/>
        <int name="category" value="24"/>
    </imgdir>
    <imgdir name="9">
        <string name="title" value="Victoria Island"/>
        <int name="category" value="30"/>
    </imgdir>
    <imgdir name="10">
        <string name="title" value="Lith Harbor"/>
        <int name="category" value="0"/>
    </imgdir>
    <imgdir name="11">
        <string name="title" value="El Nath Mts. + Aqua Road"/>
        <int name="category" value="33"/>
    </imgdir>
    <imgdir name="12">
        <string name="title" value="Ludus Lake"/>
        <int name="category" value="37"/>
    </imgdir>
    <imgdir name="13">
        <string name="title" value="Mu Lung + Nihal Desert"/>
        <int name="category" value="44"/>
    </imgdir>
    <imgdir name="14">
        <string name="title" value="Ellin Forest"/>
        <int name="category" value="39"/>
    </imgdir>
    <imgdir name="15">
        <string name="title" value="Leafre"/>
        <int name="category" value="41"/>
    </imgdir>
    <imgdir name="16">
        <string name="title" value="Temple of Time"/>
        <int name="category" value="46"/>
    </imgdir>
    <imgdir name="17">
        <string name="title" value="Gate to the Future"/>
        <int name="category" value="47"/>
    </imgdir>
    <imgdir name="18">
        <string name="title" value="Silent Crusade"/>
        <int name="category" value="1"/>
    </imgdir>
    <imgdir name="19">
        <string name="title" value="World Tour"/>
        <int name="category" value="48"/>
    </imgdir>
    <imgdir name="20">
        <string name="title" value="Party Quest"/>
        <int name="category" value="49"/>
    </imgdir>
    <imgdir name="21">
        <string name="title" value="Event"/>
        <int name="category" value="50"/>
    </imgdir>
    <imgdir name="22">
        <string name="title" value="Title"/>
        <int name="category" value="51"/>
    </imgdir>
    <imgdir name="23">
        <string name="title" value="Event Mission"/>
        <int name="category" value="52"/>
    </imgdir>
    <imgdir name="24">
        <string name="title" value="Pet"/>
        <int name="category" value="53"/>
    </imgdir>
    <imgdir name="25">
        <string name="title" value="Complete before TKTKTK"/>
        <int name="category" value="100"/>
    </imgdir>
    <imgdir name="97">
        <int name="category" value="99"/>
        <string name="title" value="Malaysia"/>
    </imgdir>
    <imgdir name="98">
        <string name="title" value="Silent Crusade"/>
        <int name="category" value="17"/>
    </imgdir>
    <imgdir name="99">
        <string name="title" value="Masteria"/>
        <int name="category" value="45"/>
    </imgdir>
</imgdir>
